searcharray/term_dict.py
searcharray/indexing.py
searcharray/__init__.py
searcharray/solr.py
searcharray/postings.py
searcharray/similarity.py
searcharray/roaringish/unique.pyx
searcharray/roaringish/search.pyi
searcharray/roaringish/popcount.pyi
searcharray/roaringish/roaringish_ops.cpython-310-aarch64-linux-gnu.so
searcharray/roaringish/merge.pyx
searcharray/roaringish/snp_ops.pxd
searcharray/roaringish/unique.pyi
searcharray/roaringish/search.cpython-310-aarch64-linux-gnu.so
searcharray/roaringish/merge.cpython-310-aarch64-linux-gnu.so
searcharray/roaringish/intersect.pyi
searcharray/roaringish/roaringish.py
searcharray/roaringish/intersect.pyx
searcharray/roaringish/roaringish_ops.pyx
searcharray/roaringish/popcount.pyx
searcharray/roaringish/spans.pyx
searcharray/roaringish/popcount.cpython-310-aarch64-linux-gnu.so
searcharray/roaringish/__init__.py
searcharray/roaringish/scatter_assign.h
searcharray/roaringish/intersect.cpython-310-aarch64-linux-gnu.so
searcharray/roaringish/merge.pyi
searcharray/roaringish/search.pyx
searcharray/roaringish/unique.cpython-310-aarch64-linux-gnu.so
searcharray/roaringish/spans.cpython-310-aarch64-linux-gnu.so
searcharray/phrase/spans.py
searcharray/phrase/bigram_freqs.py
searcharray/phrase/middle_out.py
searcharray/phrase/__init__.py
searcharray/phrase/memmap_arrays.py
searcharray/bm25/bm25.pyx
searcharray/bm25/bm25.cpython-310-aarch64-linux-gnu.so
searcharray/bm25/bm25.pyi
searcharray/bm25/__init__.py
searcharray/utils/row_viewable_matrix.py
searcharray/utils/mat_set.py
searcharray/utils/sort.py
searcharray/utils/__init__.py
searcharray/utils/bitcount.py
searcharray-0.0.73.dist-info/top_level.txt
searcharray-0.0.73.dist-info/WHEEL
searcharray-0.0.73.dist-info/RECORD
searcharray-0.0.73.dist-info/entry_points.txt
searcharray-0.0.73.dist-info/METADATA
